COPYING
MANIFEST.in
README.rst
requirements.txt
setup.cfg
setup.py
lib/dingDONG/__init__.py
lib/dingDONG/config.py
lib/dingDONG.egg-info/PKG-INFO
lib/dingDONG.egg-info/SOURCES.txt
lib/dingDONG.egg-info/dependency_links.txt
lib/dingDONG.egg-info/not-zip-safe
lib/dingDONG.egg-info/requires.txt
lib/dingDONG.egg-info/top_level.txt
lib/dingDONG/bl/__init__.py
lib/dingDONG/bl/dd.py
lib/dingDONG/bl/ddNodeExec.py
lib/dingDONG/bl/jsonParser.py
lib/dingDONG/conn/__init__.py
lib/dingDONG/conn/baseConn.py
lib/dingDONG/conn/baseConnBatch.py
lib/dingDONG/conn/baseConnManager.py
lib/dingDONG/conn/baseConnWs.py
lib/dingDONG/conn/connAccess.py
lib/dingDONG/conn/connDB.py
lib/dingDONG/conn/connDBParser.py
lib/dingDONG/conn/connDBQueries.py
lib/dingDONG/conn/connFile.py
lib/dingDONG/conn/connMongo.py
lib/dingDONG/conn/transformMethods.py
lib/dingDONG/dll/Microsoft.AnalysisServices.DLL
lib/dingDONG/dll/clrmodule.dll
lib/dingDONG/dll/clrmodule.xml
lib/dingDONG/executers/__init__.py
lib/dingDONG/executers/executeAddMsg.py
lib/dingDONG/executers/executeHTMLReport.py
lib/dingDONG/executers/executeMicrosoftOLAP.py
lib/dingDONG/executers/executeSql.py
lib/dingDONG/executers/executeVersionsGit.py
lib/dingDONG/misc/__init__.py
lib/dingDONG/misc/enums.py
lib/dingDONG/misc/globalMethods.py
lib/dingDONG/misc/installMdules.py
lib/dingDONG/misc/installMongo.py
lib/dingDONG/misc/logger.py
lib/dingDong.egg-info/PKG-INFO
lib/dingDong.egg-info/SOURCES.txt
lib/dingDong.egg-info/dependency_links.txt
lib/dingDong.egg-info/not-zip-safe
lib/dingDong.egg-info/requires.txt
lib/dingDong.egg-info/top_level.txt