Metadata-Version: 1.2
Name: dingDONG
Version: 1.0.18
Summary: Data modeling managing and transforming data
Home-page: https://github.com/biskilled/dingDONG
Author: Tal@BiSkilled.com
Author-email: Tal@BiSkilled.com
License: GPLv3+
Project-URL: Bug Tracker, https://github.com/biskilled/dingDONG/issues
Project-URL: CI: Shippable, https://app.shippable.com/github/biskilled/dingDONG
Project-URL: Documentation, https://readthedocs.org/projects/dingdong/
Project-URL: Source Code, https://github.com/biskilled/dingDONG
Keywords: ETL,Data preparation,Data modeling,Python,Integration,Mapping,ML devops,CI,CD
Platform: UNKNOWN
Classifier: Development Status :: 4 - Beta
Classifier: Environment :: Console
Classifier: Intended Audience :: Developers
Classifier: Intended Audience :: Information Technology
Classifier: Intended Audience :: System Administrators
Classifier: Topic :: System :: Systems Administration
Classifier: Topic :: Utilities
Classifier: License :: OSI Approved :: GNU General Public License v3 or later (GPLv3+)
Classifier: Natural Language :: English
Classifier: Operating System :: POSIX
Classifier: Programming Language :: Python :: 2.7
Classifier: Programming Language :: Python :: 3
Classifier: Programming Language :: Python :: 3.5
Classifier: Programming Language :: Python :: 3.6
Classifier: Programming Language :: Python :: 3.7
Classifier: Programming Language :: Python :: 3.8
Requires-Python: >=2.7,!=3.0.*,!=3.1.*,!=3.2.*,!=3.3.*,!=3.4.*
